tests/__init__.py
tests/test_zap.py
wamya/__init__.py
wamya/__main__.py
wamya/checker.py
wamya/core.py
wamya/discovery.py
wamya/installer.py
wamya/logger.py
wamya/parser.py
wamya/uninstaller.py
wamya-1.0.1.dist-info/licenses/LICENSE
wamya-1.0.1.dist-info/METADATA
wamya-1.0.1.dist-info/WHEEL
wamya-1.0.1.dist-info/entry_points.txt
wamya-1.0.1.dist-info/top_level.txt
wamya-1.0.1.dist-info/RECORD
