Metadata-Version: 2.4
Name: wamya
Version: 1.0.1
Summary: Smart pip requirements installer
Author-email: Jassem Manita <jasemmanita00@gmail.com>
License: Apache-2.0
Project-URL: Homepage, https://github.com/jassem-manita/wamya
Project-URL: Repository, https://github.com/jassem-manita/wamya
Project-URL: Issues, https://github.com/jassem-manita/wamya/issues
Classifier: Development Status :: 4 - Beta
Classifier: Intended Audience :: Developers
Classifier: Operating System :: OS Independent
Classifier: Programming Language :: Python :: 3
Classifier: Programming Language :: Python :: 3.8
Classifier: Programming Language :: Python :: 3.9
Classifier: Programming Language :: Python :: 3.10
Classifier: Programming Language :: Python :: 3.11
Classifier: Programming Language :: Python :: 3.12
Requires-Python: >=3.8
License-File: LICENSE
Provides-Extra: dev
Requires-Dist: pytest>=6.0.0; extra == "dev"
Requires-Dist: pytest-cov>=2.10.0; extra == "dev"
Requires-Dist: black>=21.0.0; extra == "dev"
Requires-Dist: flake8>=3.8.0; extra == "dev"
Requires-Dist: isort>=5.0.0; extra == "dev"
Requires-Dist: mypy>=0.800; extra == "dev"
Requires-Dist: build>=0.7.0; extra == "dev"
Requires-Dist: twine>=3.4.0; extra == "dev"
Provides-Extra: keywords
Requires-Dist: pip; extra == "keywords"
Requires-Dist: requirements; extra == "keywords"
Requires-Dist: installer; extra == "keywords"
Requires-Dist: package; extra == "keywords"
Requires-Dist: management; extra == "keywords"
Dynamic: license-file
